slice-match/__init__.py
slice-match/slice_match.py
slice_match/__init__.py
slice_match/slice_match.py
slice_match-0.2.0.dist-info/LICENSE
slice_match-0.2.0.dist-info/METADATA
slice_match-0.2.0.dist-info/WHEEL
slice_match-0.2.0.dist-info/top_level.txt
slice_match-0.2.0.dist-info/RECORD
