Metadata-Version: 2.1
Name: slice-match
Version: 0.2.0
Summary: Simple class, that simplify usage of slices in __getitem__
Home-page: https://github.com/SaelKimberly/slice-match
Download-URL: https://pypi.org/project/slice-match/
Author: SaelKimberly
Author-email: sael.kimberly@yandex.ru
License: MIT
Keywords: Slice,Match,SliceMatch
Classifier: Programming Language :: Python :: 3.10
Requires-Python: >=3.10
License-File: LICENSE
